htree/PCA.py
htree/__init__.py
htree/__version__.py
htree/conf.py
htree/embedding.py
htree/logger.py
htree/optimizer.py
htree/procrustes.py
htree/spaceform_pca_lib.py
htree/test.py
htree/test_tree.py
htree/tree_collections.py
htree/utils.py
htree-3.4.1.dist-info/LICENSE
htree-3.4.1.dist-info/METADATA
htree-3.4.1.dist-info/WHEEL
htree-3.4.1.dist-info/top_level.txt
htree-3.4.1.dist-info/RECORD
