Metadata-Version: 2.2
Name: htree
Version: 3.4.1
Summary: A library for tree reading, embedding, and analysis of phylogenetic trees
Author: Puoya Tabaghi
Author-email: ptabaghi@ucsd.edu
License: MIT
Classifier: License :: OSI Approved :: MIT License
Classifier: Programming Language :: Python :: 3
Classifier: Programming Language :: Python :: 3.10
Classifier: Programming Language :: Python :: 3.11
Requires-Python: >=3.10.16
License-File: LICENSE
Requires-Dist: numpy
Requires-Dist: scipy
Requires-Dist: matplotlib
Requires-Dist: scikit-learn
Requires-Dist: torch
Requires-Dist: treeswift
Requires-Dist: tqdm
Requires-Dist: imageio
Requires-Dist: imageio-ffmpeg
Dynamic: author
Dynamic: author-email
Dynamic: classifier
Dynamic: description
Dynamic: description-content-type
Dynamic: license
Dynamic: requires-dist
Dynamic: requires-python
Dynamic: summary
